lightning_horovod/__about__.py
lightning_horovod/__init__.py
lightning_horovod/strategy.py
lightning_Horovod-0.1.0.dev0.dist-info/LICENSE
lightning_Horovod-0.1.0.dev0.dist-info/METADATA
lightning_Horovod-0.1.0.dev0.dist-info/WHEEL
lightning_Horovod-0.1.0.dev0.dist-info/top_level.txt
lightning_Horovod-0.1.0.dev0.dist-info/RECORD
